opencompass/__init__.py
opencompass/registry.py
opencompass/datasets/GaokaoBench.py
opencompass/datasets/TheoremQA.py
opencompass/datasets/__init__.py
opencompass/datasets/afqmcd.py
opencompass/datasets/arc.py
opencompass/datasets/asmqa.py
opencompass/datasets/ax.py
opencompass/datasets/base.py
opencompass/datasets/base_loader.py
opencompass/datasets/bbh.py
opencompass/datasets/boolq.py
opencompass/datasets/bustum.py
opencompass/datasets/c3.py
opencompass/datasets/cb.py
opencompass/datasets/ccpm.py
opencompass/datasets/ceval.py
opencompass/datasets/chid.py
opencompass/datasets/civilcomments.py
opencompass/datasets/cluewsc.py
opencompass/datasets/cmnli.py
opencompass/datasets/cmrc.py
opencompass/datasets/comabb.py
opencompass/datasets/commonsenseqa.py
opencompass/datasets/copa.py
opencompass/datasets/crowspairs.py
opencompass/datasets/csl.py
opencompass/datasets/douban.py
opencompass/datasets/drcd.py
opencompass/datasets/drop.py
opencompass/datasets/duee.py
opencompass/datasets/duie.py
opencompass/datasets/eprstmt.py
opencompass/datasets/fin.py
opencompass/datasets/fin_chinese_chara.py
opencompass/datasets/fin_cls.py
opencompass/datasets/fin_code_generation.py
opencompass/datasets/fin_commonsense_qa.py
opencompass/datasets/fin_idea_generation.py
opencompass/datasets/fin_info_retrieval.py
opencompass/datasets/fin_logical_reasoning.py
opencompass/datasets/fin_math_reasoning.py
opencompass/datasets/fin_risk.py
opencompass/datasets/fin_role_play.py
opencompass/datasets/fin_style_convert.py
opencompass/datasets/fin_summary.py
opencompass/datasets/fkr.py
opencompass/datasets/flores.py
opencompass/datasets/forview.py
opencompass/datasets/govrepcrs.py
opencompass/datasets/gsm8k.py
opencompass/datasets/hellaswag.py
opencompass/datasets/huggingface.py
opencompass/datasets/humaneval.py
opencompass/datasets/iwslt2017.py
opencompass/datasets/jigsawmultilingual.py
opencompass/datasets/kdconv.py
opencompass/datasets/lambada.py
opencompass/datasets/lcsts.py
fincompass-0.1.2.dist-info/LICENSE
fincompass-0.1.2.dist-info/METADATA
fincompass-0.1.2.dist-info/WHEEL
fincompass-0.1.2.dist-info/top_level.txt
fincompass-0.1.2.dist-info/RECORD
