Metadata-Version: 2.1
Name: fincompass
Version: 0.1.2
Summary: A comprehensive toolkit for large model evaluation
Keywords: AI,NLP,in-context learning
Classifier: Programming Language :: Python :: 3.8
Classifier: Programming Language :: Python :: 3.9
Classifier: Programming Language :: Python :: 3.10
Classifier: Intended Audience :: Developers
Classifier: Intended Audience :: Education
Classifier: Intended Audience :: Science/Research
Requires-Python: >=3.8.0
License-File: LICENSE
Requires-Dist: absl-py ==1.4.0
Requires-Dist: accelerate ==0.20.3
Requires-Dist: addict ==2.4.0
Requires-Dist: aiohttp ==3.8.4
Requires-Dist: aiosignal ==1.3.1
Requires-Dist: async-timeout ==4.0.2
Requires-Dist: attrs ==23.1.0
Requires-Dist: bcrypt ==4.0.1
Requires-Dist: beautifulsoup4 ==4.12.2
Requires-Dist: boto3 ==1.28.2
Requires-Dist: botocore ==1.31.2
Requires-Dist: certifi ==2023.5.7
Requires-Dist: cffi ==1.15.1
Requires-Dist: cfgv ==3.3.1
Requires-Dist: charset-normalizer ==2.1.1
Requires-Dist: click ==8.1.4
Requires-Dist: cmake ==3.26.4
Requires-Dist: colossalai ==0.3.0
Requires-Dist: contexttimer ==0.3.3
Requires-Dist: contourpy ==1.1.0
Requires-Dist: cpm-kernels ==1.0.11
Requires-Dist: cryptography ==41.0.2
Requires-Dist: cycler ==0.11.0
Requires-Dist: datasets ==2.13.1
Requires-Dist: decorator ==5.1.1
Requires-Dist: dill ==0.3.6
Requires-Dist: distlib ==0.3.6
Requires-Dist: e ==1.4.5
Requires-Dist: et-xmlfile ==1.1.0
Requires-Dist: evaluate ==0.4.0
Requires-Dist: fabric ==3.1.0
Requires-Dist: fairscale ==0.4.13
Requires-Dist: faiss-gpu ==1.7.2
Requires-Dist: filelock ==3.12.2
Requires-Dist: fonttools ==4.41.0
Requires-Dist: frozenlist ==1.3.3
Requires-Dist: fsspec ==2023.6.0
Requires-Dist: huggingface-hub ==0.16.4
Requires-Dist: identify ==2.5.24
Requires-Dist: idna ==3.4
Requires-Dist: importlib-metadata ==6.8.0
Requires-Dist: invoke ==2.1.3
Requires-Dist: jieba ==0.42.1
Requires-Dist: Jinja2 ==3.1.2
Requires-Dist: jmespath ==1.0.1
Requires-Dist: joblib ==1.3.1
Requires-Dist: kiwisolver ==1.4.4
Requires-Dist: lit ==16.0.6
Requires-Dist: markdown-it-py ==3.0.0
Requires-Dist: MarkupSafe ==2.1.3
Requires-Dist: matplotlib ==3.7.2
Requires-Dist: mdurl ==0.1.2
Requires-Dist: mmengine ==0.8.2
Requires-Dist: mpmath ==1.3.0
Requires-Dist: multidict ==6.0.4
Requires-Dist: multiprocess ==0.70.14
Requires-Dist: networkx ==3.1
Requires-Dist: ninja ==1.11.1
Requires-Dist: nltk ==3.8
Requires-Dist: nodeenv ==1.8.0
Requires-Dist: numpy ==1.23.4
Requires-Dist: nvidia-cublas-cu11 ==11.10.3.66
Requires-Dist: nvidia-cuda-cupti-cu11 ==11.7.101
Requires-Dist: nvidia-cuda-nvrtc-cu11 ==11.7.99
Requires-Dist: nvidia-cuda-runtime-cu11 ==11.7.99
Requires-Dist: nvidia-cudnn-cu11 ==8.5.0.96
Requires-Dist: nvidia-cufft-cu11 ==10.9.0.58
Requires-Dist: nvidia-curand-cu11 ==10.2.10.91
Requires-Dist: nvidia-cusolver-cu11 ==11.4.0.1
Requires-Dist: nvidia-cusparse-cu11 ==11.7.4.91
Requires-Dist: nvidia-nccl-cu11 ==2.14.3
Requires-Dist: nvidia-nvtx-cu11 ==11.7.91
Requires-Dist: openai ==0.27.1
Requires-Dist: opencv-python ==4.8.0.74
Requires-Dist: openpyxl ==3.1.2
Requires-Dist: packaging ==23.1
Requires-Dist: pandas ==1.5.3
Requires-Dist: paramiko ==3.2.0
Requires-Dist: Pillow ==10.0.0
Requires-Dist: platformdirs ==3.8.1
Requires-Dist: pre-commit ==3.3.3
Requires-Dist: protobuf ==3.20.0
Requires-Dist: psutil ==5.9.5
Requires-Dist: pyarrow ==12.0.1
Requires-Dist: pycparser ==2.21
Requires-Dist: Pygments ==2.15.1
Requires-Dist: PyNaCl ==1.5.0
Requires-Dist: pyparsing ==3.0.9
Requires-Dist: python-dateutil ==2.8.2
Requires-Dist: pytz ==2023.3
Requires-Dist: PyYAML ==6.0
Requires-Dist: rank-bm25 ==0.2.2
Requires-Dist: regex ==2023.6.3
Requires-Dist: requests ==2.28.1
Requires-Dist: responses ==0.18.0
Requires-Dist: rich ==13.4.2
Requires-Dist: rouge-score ==0.1.2
Requires-Dist: s3transfer ==0.6.1
Requires-Dist: safetensors ==0.3.1
Requires-Dist: scikit-learn ==1.2.1
Requires-Dist: scipy ==1.11.1
Requires-Dist: sentence-transformers ==2.2.2
Requires-Dist: sentencepiece ==0.1.99
Requires-Dist: six ==1.16.0
Requires-Dist: soupsieve ==2.4.1
Requires-Dist: sympy ==1.12
Requires-Dist: tabulate ==0.9.0
Requires-Dist: termcolor ==2.3.0
Requires-Dist: threadpoolctl ==3.1.0
Requires-Dist: tiktoken ==0.4.0
Requires-Dist: tokenizers ==0.13.3
Requires-Dist: tomli ==2.0.1
Requires-Dist: torch ==2.0.1
Requires-Dist: torchvision ==0.15.2
Requires-Dist: tqdm ==4.64.1
Requires-Dist: transformers ==4.31.0
Requires-Dist: triton ==2.0.0
Requires-Dist: typing-extensions ==4.7.1
Requires-Dist: urllib3 ==1.26.16
Requires-Dist: virtualenv ==20.23.1
Requires-Dist: xxhash ==3.2.0
Requires-Dist: yapf ==0.40.1
Requires-Dist: yarl ==1.9.2
Requires-Dist: zipp ==3.16.0
